{
  "nodes": {
    "0.0": {
      "op": "OfNat.ofNat",
      "children": [],
      "eclass": "0",
      "cost": 1.0,
      "subsumed": false
    },
    "22.0": {
      "op": "const",
      "children": [
        "21.0"
      ],
      "eclass": "22",
      "cost": 1.0,
      "subsumed": false
    },
    "3.0": {
      "op": "Nat",
      "children": [],
      "eclass": "3",
      "cost": 1.0,
      "subsumed": false
    },
    "6.0": {
      "op": "const",
      "children": [
        "39.0"
      ],
      "eclass": "6",
      "cost": 1.0,
      "subsumed": false
    },
    "6.1": {
      "op": "lit",
      "children": [
        "1.0"
      ],
      "eclass": "6",
      "cost": 1.0,
      "subsumed": false
    },
    "9.0": {
      "op": "const",
      "children": [
        "8.0",
        "1.0"
      ],
      "eclass": "9",
      "cost": 1.0,
      "subsumed": false
    },
    "12.0": {
      "op": "inst",
      "children": [
        "11.0"
      ],
      "eclass": "12",
      "cost": 1.0,
      "subsumed": false
    },
    "15.0": {
      "op": "=",
      "children": [
        "14.0",
        "13.0"
      ],
      "eclass": "15",
      "cost": 1.0,
      "subsumed": false
    },
    "18.0": {
      "op": "const",
      "children": [
        "17.0"
      ],
      "eclass": "18",
      "cost": 1.0,
      "subsumed": false
    },
    "18.1": {
      "op": "app",
      "children": [
        "23.0",
        "18.0"
      ],
      "eclass": "18",
      "cost": 1.0,
      "subsumed": false
    },
    "18.2": {
      "op": "∀",
      "children": [
        "4.0",
        "15.0"
      ],
      "eclass": "18",
      "cost": 1.0,
      "subsumed": false
    },
    "18.3": {
      "op": "=",
      "children": [
        "2.0",
        "2.0"
      ],
      "eclass": "18",
      "cost": 1.0,
      "subsumed": false
    },
    "18.4": {
      "op": "=",
      "children": [
        "4.0",
        "4.0"
      ],
      "eclass": "18",
      "cost": 1.0,
      "subsumed": false
    },
    "18.5": {
      "op": "=",
      "children": [
        "5.0",
        "5.0"
      ],
      "eclass": "18",
      "cost": 1.0,
      "subsumed": false
    },
    "18.6": {
      "op": "=",
      "children": [
        "6.0",
        "6.0"
      ],
      "eclass": "18",
      "cost": 1.0,
      "subsumed": false
    },
    "18.7": {
      "op": "=",
      "children": [
        "7.0",
        "7.0"
      ],
      "eclass": "18",
      "cost": 1.0,
      "subsumed": false
    },
    "18.8": {
      "op": "=",
      "children": [
        "9.0",
        "9.0"
      ],
      "eclass": "18",
      "cost": 1.0,
      "subsumed": false
    },
    "18.9": {
      "op": "=",
      "children": [
        "10.0",
        "10.0"
      ],
      "eclass": "18",
      "cost": 1.0,
      "subsumed": false
    },
    "18.10": {
      "op": "=",
      "children": [
        "11.0",
        "11.0"
      ],
      "eclass": "18",
      "cost": 1.0,
      "subsumed": false
    },
    "18.11": {
      "op": "=",
      "children": [
        "12.0",
        "12.0"
      ],
      "eclass": "18",
      "cost": 1.0,
      "subsumed": false
    },
    "18.12": {
      "op": "=",
      "children": [
        "13.0",
        "13.0"
      ],
      "eclass": "18",
      "cost": 1.0,
      "subsumed": false
    },
    "18.13": {
      "op": "=",
      "children": [
        "14.0",
        "14.0"
      ],
      "eclass": "18",
      "cost": 1.0,
      "subsumed": false
    },
    "18.14": {
      "op": "=",
      "children": [
        "15.0",
        "15.0"
      ],
      "eclass": "18",
      "cost": 1.0,
      "subsumed": false
    },
    "18.15": {
      "op": "=",
      "children": [
        "18.0",
        "18.0"
      ],
      "eclass": "18",
      "cost": 1.0,
      "subsumed": false
    },
    "18.16": {
      "op": "=",
      "children": [
        "22.0",
        "22.0"
      ],
      "eclass": "18",
      "cost": 1.0,
      "subsumed": false
    },
    "18.17": {
      "op": "=",
      "children": [
        "23.0",
        "23.0"
      ],
      "eclass": "18",
      "cost": 1.0,
      "subsumed": false
    },
    "21.0": {
      "op": "And",
      "children": [],
      "eclass": "21",
      "cost": 1.0,
      "subsumed": false
    },
    "2.0": {
      "op": "const",
      "children": [
        "0.0",
        "1.0"
      ],
      "eclass": "2",
      "cost": 1.0,
      "subsumed": false
    },
    "5.0": {
      "op": "app",
      "children": [
        "2.0",
        "4.0"
      ],
      "eclass": "5",
      "cost": 1.0,
      "subsumed": false
    },
    "8.0": {
      "op": "OfNat",
      "children": [],
      "eclass": "8",
      "cost": 1.0,
      "subsumed": false
    },
    "11.0": {
      "op": "app",
      "children": [
        "10.0",
        "6.0"
      ],
      "eclass": "11",
      "cost": 1.0,
      "subsumed": false
    },
    "14.0": {
      "op": "bvar",
      "children": [
        "1.0"
      ],
      "eclass": "14",
      "cost": 1.0,
      "subsumed": false
    },
    "17.0": {
      "op": "True",
      "children": [],
      "eclass": "17",
      "cost": 1.0,
      "subsumed": false
    },
    "39.0": {
      "op": "Nat.zero",
      "children": [],
      "eclass": "39",
      "cost": 1.0,
      "subsumed": false
    },
    "20.0": {
      "op": "fact",
      "children": [
        "18.0"
      ],
      "eclass": "20",
      "cost": 1.0,
      "subsumed": false
    },
    "1.0": {
      "op": "0",
      "children": [],
      "eclass": "1",
      "cost": 1.0,
      "subsumed": false
    },
    "23.0": {
      "op": "app",
      "children": [
        "22.0",
        "18.0"
      ],
      "eclass": "23",
      "cost": 1.0,
      "subsumed": false
    },
    "4.0": {
      "op": "const",
      "children": [
        "3.0"
      ],
      "eclass": "4",
      "cost": 1.0,
      "subsumed": false
    },
    "7.0": {
      "op": "app",
      "children": [
        "5.0",
        "6.0"
      ],
      "eclass": "7",
      "cost": 1.0,
      "subsumed": false
    },
    "10.0": {
      "op": "app",
      "children": [
        "9.0",
        "4.0"
      ],
      "eclass": "10",
      "cost": 1.0,
      "subsumed": false
    },
    "13.0": {
      "op": "app",
      "children": [
        "7.0",
        "12.0"
      ],
      "eclass": "13",
      "cost": 1.0,
      "subsumed": false
    }
  },
  "root_eclasses": [
    "13",
    "13"
  ],
  "class_data": {}
}